create_agentverse_agent/__init__.py
create_agentverse_agent/__main__.py
create_agentverse_agent/cli.py
create_agentverse_agent/context.py
create_agentverse_agent/prompts.py
create_agentverse_agent/py.typed
create_agentverse_agent/scaffold.py
create_agentverse_agent/templates/template..env.j2
create_agentverse_agent/templates/template.Dockerfile.j2
create_agentverse_agent/templates/template.Makefile.j2
create_agentverse_agent/templates/template.README.md.j2
create_agentverse_agent/templates/template.agent.py.j2
create_agentverse_agent/templates/template.docker-compose.yml.j2
create_agentverse_agent/templates/template.main.py.j2
create_agentverse_agent/templates/template.pyproject.toml.j2
create_agentverse_agent/templates/template.test.py.j2
create_agentverse_agent/templates.py
create_agentverse_agent-0.2.7.dist-info/WHEEL
create_agentverse_agent-0.2.7.dist-info/entry_points.txt
create_agentverse_agent-0.2.7.dist-info/METADATA
create_agentverse_agent-0.2.7.dist-info/RECORD
