Metadata-Version: 2.3
Name: create-agentverse-agent
Version: 0.2.7
Summary: A tool to create Agentverse compatible agents based on uAgents framework.
Keywords: agents,agentverse,uagents,ai-agents,cli,code-generator
Author: Tejus Gupta
Author-email: Tejus Gupta <tejus3131@tejusgupta.dev>
License: MIT License
Classifier: Development Status :: 4 - Beta
Classifier: Intended Audience :: Developers
Classifier: License :: OSI Approved :: MIT License
Classifier: Programming Language :: Python :: 3
Classifier: Programming Language :: Python :: 3.12
Classifier: Programming Language :: Python :: 3.13
Classifier: Programming Language :: Python :: 3.14
Classifier: Programming Language :: Python :: Implementation :: CPython
Classifier: Topic :: Software Development :: Code Generators
Classifier: Topic :: Software Development :: Libraries
Classifier: Environment :: Console
Classifier: Typing :: Typed
Requires-Dist: jinja2>=3.1.6
Requires-Dist: pydantic>=2.12.5
Requires-Dist: rich>=14.2.0
Requires-Dist: typer>=0.21.1
Requires-Python: >=3.12
Project-URL: Homepage, https://create-agentverse-agent.tech/
Project-URL: Repository, https://github.com/tejus3131/create-agentverse-agent
Project-URL: Issues, https://github.com/tejus3131/create-agentverse-agent/issues
Project-URL: Documentation, https://create-agentverse-agent.tech/
Project-URL: Changelog, https://github.com/tejus3131/create-agentverse-agent/releases
